inkwell/__init__.py
inkwell/cli.py
inkwell/config.py
inkwell/database.py
inkwell/server.py
inkwell/api/__init__.py
inkwell/api/health/routes.py
inkwell/api/items/models.py
inkwell/api/items/routes.py
inkwell/api/projects/__init__.py
inkwell/api/projects/models.py
inkwell/api/projects/routes.py
inkwell/api/prompts/models.py
inkwell/api/prompts/routes.py
inkwell/api/settings/routes.py
inkwell/api/users/routes.py
inkwell/client_cli/__init__.py
inkwell/client_cli/main.py
inkwell/frontend/build/asset-manifest.json
inkwell/frontend/build/index.html
inkwell/frontend/build/manifest.json
inkwell/frontend/build/static/css/main.a67b7137.css
inkwell/frontend/build/static/css/main.a67b7137.css.map
inkwell/frontend/build/static/js/main.d0116042.js
inkwell/frontend/build/static/js/main.d0116042.js.LICENSE.txt
inkwell/frontend/build/static/js/main.d0116042.js.map
inkwell_app-0.1.9.dist-info/METADATA
inkwell_app-0.1.9.dist-info/WHEEL
inkwell_app-0.1.9.dist-info/entry_points.txt
inkwell_app-0.1.9.dist-info/top_level.txt
inkwell_app-0.1.9.dist-info/RECORD
